{
  "bp_condition_activity_1_1": {
    "conditionId": "bp_condition_activity_1_1",
    "progressToCompare": 1
  },
  "bp_condition_once_12": {
    "conditionId": "bp_condition_once_12",
    "progressToCompare": 3
  },
  "bp_condition_season_1_6": {
    "conditionId": "bp_condition_season_1_6",
    "progressToCompare": 1
  },
  "bp_condition_activity_1_2": {
    "conditionId": "bp_condition_activity_1_2",
    "progressToCompare": 1
  },
  "bp_condition_common_taskopen": {
    "conditionId": "bp_condition_common_taskopen",
    "progressToCompare": 1
  },
  "bp_condition_season_1_7": {
    "conditionId": "bp_condition_season_1_7",
    "progressToCompare": 20
  },
  "bp_condition_activity_1_3": {
    "conditionId": "bp_condition_activity_1_3",
    "progressToCompare": 1
  },
  "bp_condition_season_1_4": {
    "conditionId": "bp_condition_season_1_4",
    "progressToCompare": 1
  },
  "bp_condition_activity_1_4": {
    "conditionId": "bp_condition_activity_1_4",
    "progressToCompare": 1
  },
  "bp_condition_once_4_1": {
    "conditionId": "bp_condition_once_4_1",
    "progressToCompare": 1
  },
  "bp_condition_seasoncatchup_1_6_4": {
    "conditionId": "bp_condition_seasoncatchup_1_6_4",
    "progressToCompare": 1
  },
  "bp_condition_weekly_6_4": {
    "conditionId": "bp_condition_weekly_6_4",
    "progressToCompare": 1
  },
  "bp_condition_activity_1_5": {
    "conditionId": "bp_condition_activity_1_5",
    "progressToCompare": 3
  },
  "bp_condition_once_21": {
    "conditionId": "bp_condition_once_21",
    "progressToCompare": 1
  },
  "bp_condition_once_4_2": {
    "conditionId": "bp_condition_once_4_2",
    "progressToCompare": 1
  },
  "bp_condition_weekly_6_7": {
    "conditionId": "bp_condition_weekly_6_7",
    "progressToCompare": 5
  },
  "bp_condition_activity_1_6": {
    "conditionId": "bp_condition_activity_1_6",
    "progressToCompare": 5
  },
  "bp_condition_once_11": {
    "conditionId": "bp_condition_once_11",
    "progressToCompare": 3
  },
  "bp_condition_once_4_3": {
    "conditionId": "bp_condition_once_4_3",
    "progressToCompare": 1
  },
  "bp_condition_weekly_6_6": {
    "conditionId": "bp_condition_weekly_6_6",
    "progressToCompare": 1000000
  },
  "bp_condition_activity_1_7": {
    "conditionId": "bp_condition_activity_1_7",
    "progressToCompare": 7
  },
  "bp_condition_once_4_4": {
    "conditionId": "bp_condition_once_4_4",
    "progressToCompare": 1
  },
  "bp_condition_season_1_8": {
    "conditionId": "bp_condition_season_1_8",
    "progressToCompare": 10
  },
  "bp_condition_activity_1_8": {
    "conditionId": "bp_condition_activity_1_8",
    "progressToCompare": 1
  },
  "bp_condition_seasoncatchup_1_8": {
    "conditionId": "bp_condition_seasoncatchup_1_8",
    "progressToCompare": 3
  },
  "bp_condition_weekly_1_1": {
    "conditionId": "bp_condition_weekly_1_1",
    "progressToCompare": 20
  },
  "bp_condition_once_1": {
    "conditionId": "bp_condition_once_1",
    "progressToCompare": 3
  },
  "bp_condition_once_10": {
    "conditionId": "bp_condition_once_10",
    "progressToCompare": 30
  },
  "bp_condition_weekly_1_4": {
    "conditionId": "bp_condition_weekly_1_4",
    "progressToCompare": 5
  },
  "bp_condition_once_13": {
    "conditionId": "bp_condition_once_13",
    "progressToCompare": 20
  },
  "bp_condition_once_14": {
    "conditionId": "bp_condition_once_14",
    "progressToCompare": 5
  },
  "bp_condition_once_15": {
    "conditionId": "bp_condition_once_15",
    "progressToCompare": 1
  },
  "bp_condition_once_16": {
    "conditionId": "bp_condition_once_16",
    "progressToCompare": 1
  },
  "bp_condition_once_17": {
    "conditionId": "bp_condition_once_17",
    "progressToCompare": 1
  },
  "bp_condition_weekly_1_3": {
    "conditionId": "bp_condition_weekly_1_3",
    "progressToCompare": 5
  },
  "bp_condition_once_18": {
    "conditionId": "bp_condition_once_18",
    "progressToCompare": 4
  },
  "bp_condition_once_19": {
    "conditionId": "bp_condition_once_19",
    "progressToCompare": 1
  },
  "bp_condition_weekly_5_2_1": {
    "conditionId": "bp_condition_weekly_5_2_1",
    "progressToCompare": 5
  },
  "bp_condition_once_2": {
    "conditionId": "bp_condition_once_2",
    "progressToCompare": 10
  },
  "bp_condition_weekly_5_3": {
    "conditionId": "bp_condition_weekly_5_3",
    "progressToCompare": 10
  },
  "bp_condition_once_20": {
    "conditionId": "bp_condition_once_20",
    "progressToCompare": 10
  },
  "bp_condition_weekly_1_5": {
    "conditionId": "bp_condition_weekly_1_5",
    "progressToCompare": 40
  },
  "bp_condition_once_3": {
    "conditionId": "bp_condition_once_3",
    "progressToCompare": 10
  },
  "bp_condition_once_5": {
    "conditionId": "bp_condition_once_5",
    "progressToCompare": 1
  },
  "bp_condition_once_6_1": {
    "conditionId": "bp_condition_once_6_1",
    "progressToCompare": 1
  },
  "bp_condition_weekly_4_4": {
    "conditionId": "bp_condition_weekly_4_4",
    "progressToCompare": 50
  },
  "bp_condition_once_6_2": {
    "conditionId": "bp_condition_once_6_2",
    "progressToCompare": 1
  },
  "bp_condition_weekly_4_7": {
    "conditionId": "bp_condition_weekly_4_7",
    "progressToCompare": 20
  },
  "bp_condition_once_7": {
    "conditionId": "bp_condition_once_7",
    "progressToCompare": 5
  },
  "bp_condition_once_8": {
    "conditionId": "bp_condition_once_8",
    "progressToCompare": 3
  },
  "bp_condition_once_9": {
    "conditionId": "bp_condition_once_9",
    "progressToCompare": 3
  },
  "bp_condition_seasoncatchup_1_6_1": {
    "conditionId": "bp_condition_seasoncatchup_1_6_1",
    "progressToCompare": 1
  },
  "bp_condition_season_1_1": {
    "conditionId": "bp_condition_season_1_1",
    "progressToCompare": 1
  },
  "bp_condition_seasoncatchup_1_10": {
    "conditionId": "bp_condition_seasoncatchup_1_10",
    "progressToCompare": 1
  },
  "bp_condition_weekly_2_1": {
    "conditionId": "bp_condition_weekly_2_1",
    "progressToCompare": 3
  },
  "bp_condition_season_1_10": {
    "conditionId": "bp_condition_season_1_10",
    "progressToCompare": 1
  },
  "bp_condition_season_1_12": {
    "conditionId": "bp_condition_season_1_12",
    "progressToCompare": 1000
  },
  "bp_condition_season_1_11_1": {
    "conditionId": "bp_condition_season_1_11_1",
    "progressToCompare": 1
  },
  "bp_condition_season_1_11_2": {
    "conditionId": "bp_condition_season_1_11_2",
    "progressToCompare": 1
  },
  "bp_condition_weekly_5_5": {
    "conditionId": "bp_condition_weekly_5_5",
    "progressToCompare": 1
  },
  "bp_condition_season_1_13": {
    "conditionId": "bp_condition_season_1_13",
    "progressToCompare": 6
  },
  "bp_condition_season_1_17": {
    "conditionId": "bp_condition_season_1_17",
    "progressToCompare": 1
  },
  "bp_condition_season_1_14": {
    "conditionId": "bp_condition_season_1_14",
    "progressToCompare": 60
  },
  "bp_condition_season_1_16": {
    "conditionId": "bp_condition_season_1_16",
    "progressToCompare": 1
  },
  "bp_condition_season_1_18": {
    "conditionId": "bp_condition_season_1_18",
    "progressToCompare": 1
  },
  "bp_condition_season_1_2": {
    "conditionId": "bp_condition_season_1_2",
    "progressToCompare": 1
  },
  "bp_condition_weekly_2_4": {
    "conditionId": "bp_condition_weekly_2_4",
    "progressToCompare": 10
  },
  "bp_condition_season_1_3": {
    "conditionId": "bp_condition_season_1_3",
    "progressToCompare": 1
  },
  "bp_condition_weekly_2_7": {
    "conditionId": "bp_condition_weekly_2_7",
    "progressToCompare": 15
  },
  "bp_condition_season_1_5": {
    "conditionId": "bp_condition_season_1_5",
    "progressToCompare": 1
  },
  "bp_condition_weekly_2_5": {
    "conditionId": "bp_condition_weekly_2_5",
    "progressToCompare": 1
  },
  "bp_condition_season_1_9": {
    "conditionId": "bp_condition_season_1_9",
    "progressToCompare": 3
  },
  "bp_condition_seasoncatchup_1_1": {
    "conditionId": "bp_condition_seasoncatchup_1_1",
    "progressToCompare": 5
  },
  "bp_condition_weekly_4_1": {
    "conditionId": "bp_condition_weekly_4_1",
    "progressToCompare": 5
  },
  "bp_condition_seasoncatchup_1_11_1": {
    "conditionId": "bp_condition_seasoncatchup_1_11_1",
    "progressToCompare": 1
  },
  "bp_condition_seasoncatchup_1_11_2": {
    "conditionId": "bp_condition_seasoncatchup_1_11_2",
    "progressToCompare": 1
  },
  "bp_condition_seasoncatchup_1_11_3": {
    "conditionId": "bp_condition_seasoncatchup_1_11_3",
    "progressToCompare": 1
  },
  "bp_condition_seasoncatchup_1_3": {
    "conditionId": "bp_condition_seasoncatchup_1_3",
    "progressToCompare": 5
  },
  "bp_condition_seasoncatchup_1_11_4": {
    "conditionId": "bp_condition_seasoncatchup_1_11_4",
    "progressToCompare": 1
  },
  "bp_condition_weekly_5_2_3": {
    "conditionId": "bp_condition_weekly_5_2_3",
    "progressToCompare": 5
  },
  "bp_condition_seasoncatchup_1_12": {
    "conditionId": "bp_condition_seasoncatchup_1_12",
    "progressToCompare": 1
  },
  "bp_condition_weekly_2_3": {
    "conditionId": "bp_condition_weekly_2_3",
    "progressToCompare": 16
  },
  "bp_condition_seasoncatchup_1_2": {
    "conditionId": "bp_condition_seasoncatchup_1_2",
    "progressToCompare": 10
  },
  "bp_condition_seasoncatchup_1_5": {
    "conditionId": "bp_condition_seasoncatchup_1_5",
    "progressToCompare": 5
  },
  "bp_condition_seasoncatchup_1_6_2": {
    "conditionId": "bp_condition_seasoncatchup_1_6_2",
    "progressToCompare": 1
  },
  "bp_condition_seasoncatchup_1_6_3": {
    "conditionId": "bp_condition_seasoncatchup_1_6_3",
    "progressToCompare": 1
  },
  "bp_condition_seasoncatchup_1_7_1": {
    "conditionId": "bp_condition_seasoncatchup_1_7_1",
    "progressToCompare": 1
  },
  "bp_condition_seasoncatchup_1_7_2": {
    "conditionId": "bp_condition_seasoncatchup_1_7_2",
    "progressToCompare": 1
  },
  "bp_condition_weekly_4_2": {
    "conditionId": "bp_condition_weekly_4_2",
    "progressToCompare": 10
  },
  "bp_condition_seasoncatchup_1_7_3": {
    "conditionId": "bp_condition_seasoncatchup_1_7_3",
    "progressToCompare": 1
  },
  "bp_condition_seasoncatchup_1_9_1": {
    "conditionId": "bp_condition_seasoncatchup_1_9_1",
    "progressToCompare": 1
  },
  "bp_condition_seasoncatchup_1_9_2": {
    "conditionId": "bp_condition_seasoncatchup_1_9_2",
    "progressToCompare": 1
  },
  "bp_condition_weekly_1_2": {
    "conditionId": "bp_condition_weekly_1_2",
    "progressToCompare": 30
  },
  "bp_condition_weekly_1_6": {
    "conditionId": "bp_condition_weekly_1_6",
    "progressToCompare": 30
  },
  "bp_condition_weekly_1_7": {
    "conditionId": "bp_condition_weekly_1_7",
    "progressToCompare": 3
  },
  "bp_condition_weekly_2_2": {
    "conditionId": "bp_condition_weekly_2_2",
    "progressToCompare": 10
  },
  "bp_condition_weekly_2_6": {
    "conditionId": "bp_condition_weekly_2_6",
    "progressToCompare": 30
  },
  "bp_condition_weekly_3_1": {
    "conditionId": "bp_condition_weekly_3_1",
    "progressToCompare": 5
  },
  "bp_condition_weekly_3_2": {
    "conditionId": "bp_condition_weekly_3_2",
    "progressToCompare": 200
  },
  "bp_condition_weekly_3_3": {
    "conditionId": "bp_condition_weekly_3_3",
    "progressToCompare": 50
  },
  "bp_condition_weekly_3_4": {
    "conditionId": "bp_condition_weekly_3_4",
    "progressToCompare": 50000
  },
  "bp_condition_weekly_3_5": {
    "conditionId": "bp_condition_weekly_3_5",
    "progressToCompare": 1
  },
  "bp_condition_weekly_3_6": {
    "conditionId": "bp_condition_weekly_3_6",
    "progressToCompare": 30
  },
  "bp_condition_weekly_3_7": {
    "conditionId": "bp_condition_weekly_3_7",
    "progressToCompare": 3
  },
  "bp_condition_weekly_4_3": {
    "conditionId": "bp_condition_weekly_4_3",
    "progressToCompare": 4
  },
  "bp_condition_weekly_4_5": {
    "conditionId": "bp_condition_weekly_4_5",
    "progressToCompare": 10
  },
  "bp_condition_weekly_4_6": {
    "conditionId": "bp_condition_weekly_4_6",
    "progressToCompare": 500000
  },
  "bp_condition_weekly_5_1": {
    "conditionId": "bp_condition_weekly_5_1",
    "progressToCompare": 10
  },
  "bp_condition_weekly_5_2_2": {
    "conditionId": "bp_condition_weekly_5_2_2",
    "progressToCompare": 5
  },
  "bp_condition_weekly_5_4": {
    "conditionId": "bp_condition_weekly_5_4",
    "progressToCompare": 1
  },
  "bp_condition_weekly_5_6": {
    "conditionId": "bp_condition_weekly_5_6",
    "progressToCompare": 30
  },
  "bp_condition_weekly_5_7": {
    "conditionId": "bp_condition_weekly_5_7",
    "progressToCompare": 3
  },
  "bp_condition_weekly_6_1": {
    "conditionId": "bp_condition_weekly_6_1",
    "progressToCompare": 10
  },
  "bp_condition_weekly_6_2": {
    "conditionId": "bp_condition_weekly_6_2",
    "progressToCompare": 30
  },
  "bp_condition_weekly_6_3": {
    "conditionId": "bp_condition_weekly_6_3",
    "progressToCompare": 50
  }
}