{
  "apRecoverValue": 40,
  "apRecoverValueByMoney": 40,
  "doubleStaminaTicketItemId": "item_bp_double_reward",
  "dungeonChestCollectionTag": "TrchestCommon",
  "dungeonFactoryCategory": "dungeon_factory",
  "dungeonTrainEmptyTabCount": 1,
  "dungeonTrainSeriesIds": [
    "dung_group_train01",
    "dung_group_chartrain"
  ],
  "emptyLunchBoxItemId": "item_ap_feed_in",
  "fullLunchBoxItemId": "item_ap_take_out",
  "hunterModeRequiredWorldLevel": 5,
  "initStaminaLimit": 125,
  "maxFullLunchBoxCount": 10,
  "recoverApByMoneyDailyLimit": 0,
  "recoverApMoneyId": "item_originium_recharge",
  "restoreStaminaInAnEmptyLunchBox": 120,
  "staminaCapacity": 1000,
  "staminaItemId": "item_ap",
  "staminaPerDoubleStaminaTicket": 10,
  "staminaRecoverDuration": 432,
  "staminaRecoverValue": 1
}