{
  "wpn_claym_0003": {
    "perfectGemId": "gem_claym_0003_663",
    "weaponId": "wpn_claym_0003"
  },
  "wpn_claym_0009": {
    "perfectGemId": "gem_claym_0009_663",
    "weaponId": "wpn_claym_0009"
  },
  "wpn_lance_0013": {
    "perfectGemId": "gem_lance_0013_663",
    "weaponId": "wpn_lance_0013"
  },
  "wpn_claym_0004": {
    "perfectGemId": "gem_claym_0004_663",
    "weaponId": "wpn_claym_0004"
  },
  "wpn_lance_0012": {
    "perfectGemId": "gem_lance_0012_663",
    "weaponId": "wpn_lance_0012"
  },
  "wpn_pistol_0012": {
    "perfectGemId": "gem_pistol_0012_663",
    "weaponId": "wpn_pistol_0012"
  },
  "wpn_claym_0006": {
    "perfectGemId": "gem_claym_0006_663",
    "weaponId": "wpn_claym_0006"
  },
  "wpn_lance_0010": {
    "perfectGemId": "gem_lance_0010_663",
    "weaponId": "wpn_lance_0010"
  },
  "wpn_claym_0007": {
    "perfectGemId": "gem_claym_0007_663",
    "weaponId": "wpn_claym_0007"
  },
  "wpn_funnel_0007": {
    "perfectGemId": "gem_funnel_0007_663",
    "weaponId": "wpn_funnel_0007"
  },
  "wpn_claym_0008": {
    "perfectGemId": "gem_claym_0008_663",
    "weaponId": "wpn_claym_0008"
  },
  "wpn_claym_0011": {
    "perfectGemId": "gem_claym_0011_663",
    "weaponId": "wpn_claym_0011"
  },
  "wpn_funnel_0011": {
    "perfectGemId": "gem_funnel_0011_663",
    "weaponId": "wpn_funnel_0011"
  },
  "wpn_claym_0012": {
    "perfectGemId": "gem_claym_0012_663",
    "weaponId": "wpn_claym_0012"
  },
  "wpn_pistol_0002": {
    "perfectGemId": "gem_pistol_0002_663",
    "weaponId": "wpn_pistol_0002"
  },
  "wpn_claym_0013": {
    "perfectGemId": "gem_claym_0013_663",
    "weaponId": "wpn_claym_0013"
  },
  "wpn_claym_0014": {
    "perfectGemId": "gem_claym_0014_663",
    "weaponId": "wpn_claym_0014"
  },
  "wpn_claym_0015": {
    "perfectGemId": "gem_claym_0015_663",
    "weaponId": "wpn_claym_0015"
  },
  "wpn_funnel_0001": {
    "perfectGemId": "gem_funnel_0001_663",
    "weaponId": "wpn_funnel_0001"
  },
  "wpn_funnel_0003": {
    "perfectGemId": "gem_funnel_0003_663",
    "weaponId": "wpn_funnel_0003"
  },
  "wpn_lance_0006": {
    "perfectGemId": "gem_lance_0006_663",
    "weaponId": "wpn_lance_0006"
  },
  "wpn_funnel_0004": {
    "perfectGemId": "gem_funnel_0004_663",
    "weaponId": "wpn_funnel_0004"
  },
  "wpn_funnel_0005": {
    "perfectGemId": "gem_funnel_0005_663",
    "weaponId": "wpn_funnel_0005"
  },
  "wpn_funnel_0006": {
    "perfectGemId": "gem_funnel_0006_663",
    "weaponId": "wpn_funnel_0006"
  },
  "wpn_funnel_0008": {
    "perfectGemId": "gem_funnel_0008_663",
    "weaponId": "wpn_funnel_0008"
  },
  "wpn_funnel_0009": {
    "perfectGemId": "gem_funnel_0009_663",
    "weaponId": "wpn_funnel_0009"
  },
  "wpn_funnel_0010": {
    "perfectGemId": "gem_funnel_0010_663",
    "weaponId": "wpn_funnel_0010"
  },
  "wpn_lance_0008": {
    "perfectGemId": "gem_lance_0008_663",
    "weaponId": "wpn_lance_0008"
  },
  "wpn_funnel_0012": {
    "perfectGemId": "gem_funnel_0012_663",
    "weaponId": "wpn_funnel_0012"
  },
  "wpn_sword_0013": {
    "perfectGemId": "gem_sword_0013_663",
    "weaponId": "wpn_sword_0013"
  },
  "wpn_sword_0015": {
    "perfectGemId": "gem_sword_0015_663",
    "weaponId": "wpn_sword_0015"
  },
  "wpn_sword_0019": {
    "perfectGemId": "gem_sword_0019_663",
    "weaponId": "wpn_sword_0019"
  },
  "wpn_funnel_0013": {
    "perfectGemId": "gem_funnel_0013_663",
    "weaponId": "wpn_funnel_0013"
  },
  "wpn_sword_0005": {
    "perfectGemId": "gem_sword_0005_663",
    "weaponId": "wpn_sword_0005"
  },
  "wpn_funnel_0014": {
    "perfectGemId": "gem_funnel_0014_663",
    "weaponId": "wpn_funnel_0014"
  },
  "wpn_lance_0011": {
    "perfectGemId": "gem_lance_0011_663",
    "weaponId": "wpn_lance_0011"
  },
  "wpn_lance_0003": {
    "perfectGemId": "gem_lance_0003_663",
    "weaponId": "wpn_lance_0003"
  },
  "wpn_sword_0007": {
    "perfectGemId": "gem_sword_0007_663",
    "weaponId": "wpn_sword_0007"
  },
  "wpn_lance_0004": {
    "perfectGemId": "gem_lance_0004_663",
    "weaponId": "wpn_lance_0004"
  },
  "wpn_pistol_0004": {
    "perfectGemId": "gem_pistol_0004_663",
    "weaponId": "wpn_pistol_0004"
  },
  "wpn_sword_0006": {
    "perfectGemId": "gem_sword_0006_663",
    "weaponId": "wpn_sword_0006"
  },
  "wpn_pistol_0003": {
    "perfectGemId": "gem_pistol_0003_663",
    "weaponId": "wpn_pistol_0003"
  },
  "wpn_pistol_0005": {
    "perfectGemId": "gem_pistol_0005_663",
    "weaponId": "wpn_pistol_0005"
  },
  "wpn_sword_0010": {
    "perfectGemId": "gem_sword_0010_663",
    "weaponId": "wpn_sword_0010"
  },
  "wpn_sword_0012": {
    "perfectGemId": "gem_sword_0012_663",
    "weaponId": "wpn_sword_0012"
  },
  "wpn_sword_0016": {
    "perfectGemId": "gem_sword_0016_663",
    "weaponId": "wpn_sword_0016"
  },
  "wpn_pistol_0006": {
    "perfectGemId": "gem_pistol_0006_663",
    "weaponId": "wpn_pistol_0006"
  },
  "wpn_sword_0020": {
    "perfectGemId": "gem_sword_0020_663",
    "weaponId": "wpn_sword_0020"
  },
  "wpn_pistol_0007": {
    "perfectGemId": "gem_pistol_0007_663",
    "weaponId": "wpn_pistol_0007"
  },
  "wpn_pistol_0008": {
    "perfectGemId": "gem_pistol_0008_663",
    "weaponId": "wpn_pistol_0008"
  },
  "wpn_pistol_0009": {
    "perfectGemId": "gem_pistol_0009_663",
    "weaponId": "wpn_pistol_0009"
  },
  "wpn_pistol_0010": {
    "perfectGemId": "gem_pistol_0010_663",
    "weaponId": "wpn_pistol_0010"
  },
  "wpn_sword_0008": {
    "perfectGemId": "gem_sword_0008_663",
    "weaponId": "wpn_sword_0008"
  },
  "wpn_sword_0009": {
    "perfectGemId": "gem_sword_0009_663",
    "weaponId": "wpn_sword_0009"
  },
  "wpn_sword_0011": {
    "perfectGemId": "gem_sword_0011_663",
    "weaponId": "wpn_sword_0011"
  },
  "wpn_sword_0014": {
    "perfectGemId": "gem_sword_0014_663",
    "weaponId": "wpn_sword_0014"
  },
  "wpn_sword_0018": {
    "perfectGemId": "gem_sword_0018_663",
    "weaponId": "wpn_sword_0018"
  },
  "wpn_sword_0021": {
    "perfectGemId": "gem_sword_0021_663",
    "weaponId": "wpn_sword_0021"
  }
}