{
  "aglina_base01_lv001": "chr_0013_aglina",
  "antal_base01_lv001": "chr_0023_antal",
  "ardelia_base01_lv001": "chr_0025_ardelia",
  "aurora_base01_lv001": "chr_0014_aurora",
  "meurs_base01_lv001": "chr_0020_meurs",
  "pelica_base01_lv001": "chr_0004_pelica",
  "avywen_base01_lv001": "chr_0012_avywen",
  "chen_base01_lv001": "chr_0005_chen",
  "lastrite_base01_lv001": "chr_0026_lastrite",
  "azrila_base01_lv001": "chr_0009_azrila",
  "karin_base01_lv001": "chr_0019_karin",
  "bounda_base01_lv001": "chr_0022_bounda",
  "dapan_base01_lv001": "chr_0018_dapan",
  "deepfin_base01_lv001": "chr_0024_deepfin",
  "ikut_base01_lv001": "chr_0007_ikut",
  "laevat_base01_lv001": "chr_0016_laevat",
  "lifeng_base01_lv001": "chr_0015_lifeng",
  "pograni_base01_lv001": "chr_0029_pograni",
  "seraph_base01_lv001": "chr_0011_seraph",
  "whiten_base01_lv001": "chr_0021_whiten",
  "yvonne_base01_lv001": "chr_0017_yvonne",
  "wolfgd_base01_lv001": "chr_0006_wolfgd"
}